bourbaki/__init__.py
bourbaki/introspection/__init__.py
bourbaki/introspection/builtin_signatures.py
bourbaki/introspection/callables.py
bourbaki/introspection/classes.py
bourbaki/introspection/debug.py
bourbaki/introspection/docstrings.py
bourbaki/introspection/generic_dispatch.py
bourbaki/introspection/generic_dispatch_helpers.py
bourbaki/introspection/imports.py
bourbaki/introspection/polymorphism.py
bourbaki/introspection/prettyprint.py
bourbaki/introspection/references.py
bourbaki/introspection/simple_repr.py
bourbaki/introspection/subclassing.py
bourbaki/introspection/typechecking.py
bourbaki/introspection/utils.py
bourbaki/introspection/wrappers.py
bourbaki/introspection/object_models/__init__.py
bourbaki/introspection/object_models/scala.py
bourbaki/introspection/types/__init__.py
bourbaki/introspection/types/abcs.py
bourbaki/introspection/types/compat.py
bourbaki/introspection/types/debug.py
bourbaki/introspection/types/evaluation.py
bourbaki/introspection/types/inspection.py
bourbaki/introspection/types/issubclass_generic_.py
bourbaki.introspection-0.5.11.dist-info/LICENSE
bourbaki.introspection-0.5.11.dist-info/METADATA
bourbaki.introspection-0.5.11.dist-info/WHEEL
bourbaki.introspection-0.5.11.dist-info/top_level.txt
bourbaki.introspection-0.5.11.dist-info/zip-safe
bourbaki.introspection-0.5.11.dist-info/RECORD
