Metadata-Version: 2.1
Name: bourbaki.introspection
Version: 0.5.11
Summary: UNKNOWN
Home-page: https://github.com/bourbaki-py
Author: Matthew Hawthorn
Author-email: hawthorn.matthew@gmail.com
License: Apache License 2.0
Platform: UNKNOWN
Classifier: Programming Language :: Python :: 3
Classifier: Programming Language :: Python :: 3.7
Classifier: Programming Language :: Python :: 3.8
Classifier: License :: OSI Approved :: Apache Software License
Classifier: Operating System :: POSIX :: Linux
Classifier: Operating System :: MacOS :: MacOS X
Classifier: Topic :: Software Development :: Libraries :: Python Modules
Classifier: Topic :: Software Development :: Code Generators
Classifier: Topic :: Utilities
Classifier: Typing :: Typed
Requires-Dist: multipledispatch (>=0.4.9)
Requires-Dist: typing-inspect (>=0.5)
Provides-Extra: viz
Requires-Dist: graphviz ; extra == 'viz'
Requires-Dist: networkx ; extra == 'viz'
